betterLogger/__init__.py
betterLogger/classWithLogger.py
betterLogger/colors.py
betterLogger/config.py
betterLogger/consoleHandler.py
betterLogger/fileHandler.py
betterLogger/filter.py
betterLogger/format_funcs.py
betterLogger/formatter.py
betterLogger-1.6.dist-info/LICENSE
betterLogger-1.6.dist-info/METADATA
betterLogger-1.6.dist-info/WHEEL
betterLogger-1.6.dist-info/entry_points.txt
betterLogger-1.6.dist-info/top_level.txt
betterLogger-1.6.dist-info/RECORD
