Metadata-Version: 2.1
Name: betterLogger
Version: 1.6
Summary: A great colored logger!
Home-page: https://github.com/GreenJon902/betterLogger
Author: GreenJon
Author-email: GreenJon902@gmail.com
License: MIT
Platform: UNKNOWN
Classifier: License :: OSI Approved :: MIT License
Classifier: Programming Language :: Python :: 3
Classifier: Programming Language :: Python :: 3.7
Classifier: Programming Language :: Python :: 3.9
License-File: LICENSE
Requires-Dist: appdirs
